swagger_coverage_tool/__init__.py
swagger_coverage_tool/config.py
swagger_coverage_tool/cli/__init__.py
swagger_coverage_tool/cli/main.py
swagger_coverage_tool/cli/commands/__init__.py
swagger_coverage_tool/cli/commands/copy_report.py
swagger_coverage_tool/cli/commands/print_config.py
swagger_coverage_tool/cli/commands/save_report.py
swagger_coverage_tool/src/__init__.py
swagger_coverage_tool/src/coverage/__init__.py
swagger_coverage_tool/src/coverage/builder.py
swagger_coverage_tool/src/coverage/models.py
swagger_coverage_tool/src/coverage/status.py
swagger_coverage_tool/src/history/__init__.py
swagger_coverage_tool/src/history/builder.py
swagger_coverage_tool/src/history/endpoint.py
swagger_coverage_tool/src/history/models.py
swagger_coverage_tool/src/history/storage.py
swagger_coverage_tool/src/reports/__init__.py
swagger_coverage_tool/src/reports/models.py
swagger_coverage_tool/src/reports/storage.py
swagger_coverage_tool/src/reports/templates/__init__.py
swagger_coverage_tool/src/reports/templates/index.html
swagger_coverage_tool/src/swagger/__init__.py
swagger_coverage_tool/src/swagger/core.py
swagger_coverage_tool/src/swagger/models.py
swagger_coverage_tool/src/tools/__init__.py
swagger_coverage_tool/src/tools/http.py
swagger_coverage_tool/src/tools/logger.py
swagger_coverage_tool/src/tools/percent.py
swagger_coverage_tool/src/tools/types.py
swagger_coverage_tool/src/tracker/__init__.py
swagger_coverage_tool/src/tracker/core.py
swagger_coverage_tool/src/tracker/models.py
swagger_coverage_tool/src/tracker/storage.py
swagger_coverage_tool/tests/__init__.py
swagger_coverage_tool/tests/fixtures/__init__.py
swagger_coverage_tool/tests/fixtures/config.py
swagger_coverage_tool/tests/fixtures/coverage.py
swagger_coverage_tool/tests/fixtures/history.py
swagger_coverage_tool/tests/fixtures/http.py
swagger_coverage_tool/tests/fixtures/reports.py
swagger_coverage_tool/tests/fixtures/tracker.py
swagger_coverage_tool/tests/suites/__init__.py
swagger_coverage_tool-0.30.0.dist-info/licenses/LICENSE
swagger_coverage_tool-0.30.0.dist-info/METADATA
swagger_coverage_tool-0.30.0.dist-info/WHEEL
swagger_coverage_tool-0.30.0.dist-info/entry_points.txt
swagger_coverage_tool-0.30.0.dist-info/top_level.txt
swagger_coverage_tool-0.30.0.dist-info/RECORD
