Metadata-Version: 2.4
Name: swagger-coverage-tool
Version: 0.30.0
Summary: A tool for measuring API test coverage based on Swagger
Author-email: Nikita Filonov <filonov.nikitkaa@gmail.com>
Maintainer-email: Nikita Filonov <filonov.nikitkaa@gmail.com>
License: MIT
Project-URL: Homepage, https://github.com/Nikita-Filonov/swagger-coverage-tool
Project-URL: Repository, https://github.com/Nikita-Filonov/swagger-coverage-tool
Project-URL: Issues, https://github.com/Nikita-Filonov/swagger-coverage-tool/issues
Keywords: swagger,coverage,testing,api,openapi
Classifier: Programming Language :: Python :: 3
Classifier: Programming Language :: Python :: 3.11
Classifier: Programming Language :: Python :: 3.12
Classifier: License :: OSI Approved :: MIT License
Classifier: Operating System :: OS Independent
Classifier: Intended Audience :: Developers
Classifier: Topic :: Software Development :: Testing
Classifier: Topic :: Software Development :: Quality Assurance
Requires-Python: >=3.11
License-File: LICENSE
Requires-Dist: click==8.1.8
Requires-Dist: httpx==0.28.1
Requires-Dist: pyyaml==6.0.2
Requires-Dist: pydantic==2.11.2
Requires-Dist: pydantic-settings==2.8.1
Requires-Dist: requests==2.32.3
Provides-Extra: test
Requires-Dist: pytest; extra == "test"
Requires-Dist: pytest-cov; extra == "test"
Dynamic: license-file
